some_crypt/__init__.py
some_crypt/ciphers/__init__.py
some_crypt/ciphers/autokey.py
some_crypt/ciphers/caesar.py
some_crypt/ciphers/vigenere.py
some_crypt/tests/__init__.py
some_crypt/tests/autokey_tests.py
some_crypt/tests/caesar_tests.py
some_crypt/tests/vigenere_tests.py
some_crypt/util/__init__.py
some_crypt/util/file_io.py
some_crypt/util/functional.py
some_crypt-0.1.0.dist-info/LICENSE
some_crypt-0.1.0.dist-info/METADATA
some_crypt-0.1.0.dist-info/WHEEL
some_crypt-0.1.0.dist-info/top_level.txt
some_crypt-0.1.0.dist-info/RECORD
