Metadata-Version: 2.1
Name: some-crypt
Version: 0.1.0
Summary: A simple (and simplistic) basic cryptography package
Home-page: https://github.com/Grimmslaw/some_crypt.git
Author: Wes Rickey
Author-email: d.wrickey@gmail.com
License: UNKNOWN
Platform: UNKNOWN
Classifier: Programming Language :: Python :: 3
Classifier: License :: OSI Approved :: MIT License
Classifier: Operating System :: OS Independent
